newpro_autoloader/__init__.py
newpro_autoloader/axis_status.py
newpro_autoloader/connection.py
newpro_autoloader/device_error.py
newpro_autoloader/loader.py
newpro_autoloader/loader_connection.py
newpro_autoloader-0.0.1.dist-info/METADATA
newpro_autoloader-0.0.1.dist-info/WHEEL
newpro_autoloader-0.0.1.dist-info/licenses/LICENSE
newpro_autoloader-0.0.1.dist-info/RECORD
