Metadata-Version: 2.4
Name: newpro-autoloader
Version: 0.0.1
Summary: Interface to NewPro's TEM/SEM Autoloader
Project-URL: Homepage, https://newproip.com
Project-URL: Repository, https://github.com/newproip/autoloader
Project-URL: Issues, https://github.com/newproip/autoloader/issues
Author-email: Jacob Lipcon <jlipcon@newproip.com>
License-File: LICENSE
Classifier: Development Status :: 4 - Beta
Classifier: Operating System :: OS Independent
Classifier: Programming Language :: Python :: 3
Classifier: Topic :: Scientific/Engineering
Requires-Python: >=3.8
